odoo/addons/stock_account_product_cost_security/README.rst
odoo/addons/stock_account_product_cost_security/__init__.py
odoo/addons/stock_account_product_cost_security/__manifest__.py
odoo/addons/stock_account_product_cost_security/data/product_cost_security.xml
odoo/addons/stock_account_product_cost_security/i18n/ca.po
odoo/addons/stock_account_product_cost_security/i18n/es.po
odoo/addons/stock_account_product_cost_security/i18n/stock_account_product_cost_security.pot
odoo/addons/stock_account_product_cost_security/migrations/13.0.3.0.0/post-migrate.py
odoo/addons/stock_account_product_cost_security/models/__init__.py
odoo/addons/stock_account_product_cost_security/models/product_template.py
odoo/addons/stock_account_product_cost_security/readme/CONFIGURE.rst
odoo/addons/stock_account_product_cost_security/readme/CONTRIBUTORS.rst
odoo/addons/stock_account_product_cost_security/readme/DESCRIPTION.rst
odoo/addons/stock_account_product_cost_security/readme/INSTALL.rst
odoo/addons/stock_account_product_cost_security/static/description/icon.png
odoo/addons/stock_account_product_cost_security/static/description/index.html
odoo/addons/stock_account_product_cost_security/views/product_views.xml
odoo/addons/stock_account_product_cost_security/wizard/stock_change_standard_price_views.xml
odoo13_addon_stock_account_product_cost_security-13.0.3.1.0.dist-info/METADATA
odoo13_addon_stock_account_product_cost_security-13.0.3.1.0.dist-info/WHEEL
odoo13_addon_stock_account_product_cost_security-13.0.3.1.0.dist-info/top_level.txt
odoo13_addon_stock_account_product_cost_security-13.0.3.1.0.dist-info/RECORD
