Metadata-Version: 2.1
Name: odoo13-addon-stock-account-product-cost-security
Version: 13.0.3.1.0
Summary: Product cost security restriction view
Home-page: https://github.com/OCA/product-attribute
Author: Tecnativa, Odoo Community Association (OCA)
Author-email: support@odoo-community.org
License: AGPL-3
Platform: UNKNOWN
Classifier: Programming Language :: Python
Classifier: Framework :: Odoo
Classifier: Framework :: Odoo :: 13.0
Classifier: License :: OSI Approved :: GNU Affero General Public License v3
Classifier: Development Status :: 4 - Beta
Requires-Python: >=3.5
Requires-Dist: odoo13-addon-product-cost-security
Requires-Dist: odoo (<13.1dev,>=13.0a)
